i18nize_templates/__init__.py
i18nize_templates-0.2.dist-info/DESCRIPTION.rst
i18nize_templates-0.2.dist-info/METADATA
i18nize_templates-0.2.dist-info/RECORD
i18nize_templates-0.2.dist-info/WHEEL
i18nize_templates-0.2.dist-info/entry_points.txt
i18nize_templates-0.2.dist-info/metadata.json
i18nize_templates-0.2.dist-info/top_level.txt
