Metadata-Version: 2.0
Name: i18nize-templates
Version: 0.2
Summary: Adds i18n markup to jinja2 and handlebars templates.
Home-page: https://github.com/csilvers/i18nize_templates
Author: Craig Silverstein
Author-email: csilvers+i18nize_templates@gmail.com
License: MIT
Keywords: i18n jinja jinja2 handlebars translation
Platform: any
Classifier: Development Status :: 4 - Beta
Classifier: Environment :: Web Environment
Classifier: Intended Audience :: Developers
Classifier: License :: OSI Approved :: MIT License
Classifier: Operating System :: OS Independent
Classifier: Programming Language :: Python
Classifier: Topic :: Software Development :: Internationalization
Classifier: Topic :: Software Development :: Libraries :: Python Modules
